{
  "symbol": "ETHUSDT",
  "timestamp": "2026-03-02T05:47:28.118581",
  "overall_bias": "bearish",
  "confidence": 57.14285714285714,
  "timeframe_analysis": {
    "1M": {
      "interval": "1M",
      "trend": "neutral",
      "trend_strength": 50,
      "rsi": 39.09473123214259,
      "ema20": 2785.551955500005,
      "ema50": 2459.5072888244636,
      "key_levels": {
        "high": 4956.78,
        "low": 1385.05
      },
      "fib_levels": {
        "0.0": 4956.78,
        "0.236": 4113.85172,
        "0.382": 3592.37914,
        "0.5": 3170.915,
        "0.618": 2749.45086,
        "0.786": 2149.40022,
        "1.0": 1385.05
      },
      "latest_close": 1965.28,
      "higher_tf_bias": "unknown",
      "alignment_with_higher_tf": "misaligned"
    },
    "1w": {
      "interval": "1w",
      "trend": "bearish",
      "trend_strength": 130.0,
      "rsi": 25.99149812781515,
      "ema20": 2792.6866324662574,
      "ema50": 3019.9730102946974,
      "key_levels": {
        "high": 4292.0,
        "low": 1747.8
      },
      "fib_levels": {
        "0.0": 4292.0,
        "0.236": 3691.5688,
        "0.382": 3320.1156,
        "0.5": 3019.9,
        "0.618": 2719.6844,
        "0.786": 2292.2588,
        "1.0": 1747.8
      },
      "latest_close": 1864.5,
      "higher_tf_bias": "bearish",
      "alignment_with_higher_tf": "aligned",
      "near_higher_tf_level": "none",
      "confidence": "high"
    },
    "1d": {
      "interval": "1d",
      "trend": "bearish",
      "trend_strength": 130.0,
      "rsi": 38.69546498277841,
      "ema20": 2025.539596988032,
      "ema50": 2326.144547994565,
      "key_levels": {
        "high": 2124.71,
        "low": 1847.41
      },
      "fib_levels": {
        "0.0": 2124.71,
        "0.236": 2059.2672000000002,
        "0.382": 2018.7814,
        "0.5": 1986.06,
        "0.618": 1953.3386,
        "0.786": 1906.7522000000001,
        "1.0": 1847.41
      },
      "latest_close": 1965.28,
      "higher_tf_bias": "bearish",
      "alignment_with_higher_tf": "aligned",
      "near_higher_tf_level": "none",
      "confidence": "high"
    },
    "4h": {
      "interval": "4h",
      "trend": "neutral",
      "trend_strength": 35.0,
      "rsi": 48.88171925411497,
      "ema20": 1963.1078692601093,
      "ema50": 1961.5346955934058,
      "key_levels": {
        "high": 2063.52,
        "low": 1835.36
      },
      "fib_levels": {
        "0.0": 2063.52,
        "0.236": 2009.67424,
        "0.382": 1976.36288,
        "0.5": 1949.44,
        "0.618": 1922.51712,
        "0.786": 1884.18624,
        "1.0": 1835.36
      },
      "latest_close": 1953.72,
      "higher_tf_bias": "bearish",
      "alignment_with_higher_tf": "misaligned",
      "near_higher_tf_level": "none",
      "at_higher_tf_fib": "0.618",
      "higher_tf_fib_price": 1953.3386,
      "confidence": "low"
    },
    "1h": {
      "interval": "1h",
      "trend": "neutral",
      "trend_strength": 35.0,
      "rsi": 28.545204222120134,
      "ema20": 1965.4155401633693,
      "ema50": 1962.647042704701,
      "key_levels": {
        "high": 2054.8,
        "low": 1907.41
      },
      "fib_levels": {
        "0.0": 2054.8,
        "0.236": 2020.0159600000002,
        "0.382": 1998.4970200000002,
        "0.5": 1981.105,
        "0.618": 1963.71298,
        "0.786": 1938.95146,
        "1.0": 1907.41
      },
      "latest_close": 1914.84,
      "higher_tf_bias": "bearish",
      "alignment_with_higher_tf": "misaligned",
      "near_higher_tf_level": "none",
      "at_higher_tf_fib": "0.618",
      "higher_tf_fib_price": 1922.51712,
      "confidence": "low"
    },
    "15m": {
      "interval": "15m",
      "trend": "bearish",
      "trend_strength": 14.593063481455127,
      "rsi": 18.17395067070531,
      "ema20": 1946.3901177642529,
      "ema50": 1966.1007294458693,
      "key_levels": {
        "high": 1997.53,
        "low": 1907.41
      },
      "fib_levels": {
        "0.0": 1997.53,
        "0.236": 1976.26168,
        "0.382": 1963.10416,
        "0.5": 1952.47,
        "0.618": 1941.83584,
        "0.786": 1926.69568,
        "1.0": 1907.41
      },
      "latest_close": 1925.95,
      "higher_tf_bias": "bullish",
      "alignment_with_higher_tf": "misaligned",
      "near_higher_tf_level": "low",
      "higher_tf_level_value": 1907.41,
      "at_higher_tf_fib": "0.786",
      "higher_tf_fib_price": 1938.95146,
      "confidence": "low"
    },
    "5m": {
      "interval": "5m",
      "trend": "bearish",
      "trend_strength": 12.759038430472192,
      "rsi": 56.899810964083315,
      "ema20": 1927.9383992184273,
      "ema50": 1944.8525154347446,
      "key_levels": {
        "high": 1943.16,
        "low": 1907.41
      },
      "fib_levels": {
        "0.0": 1943.16,
        "0.236": 1934.7230000000002,
        "0.382": 1929.5035,
        "0.5": 1925.285,
        "0.618": 1921.0665000000001,
        "0.786": 1915.0605,
        "1.0": 1907.41
      },
      "latest_close": 1925.95,
      "higher_tf_bias": "bearish",
      "alignment_with_higher_tf": "aligned",
      "near_higher_tf_level": "low",
      "higher_tf_level_value": 1907.41,
      "at_higher_tf_fib": "0.618",
      "higher_tf_fib_price": 1941.83584,
      "confidence": "high"
    }
  },
  "trade_setup": null
}