{
  "symbol": "ETHUSDT",
  "timestamp": "2026-03-02T23:11:12.502268",
  "overall_bias": "bearish",
  "confidence": 42.857142857142854,
  "timeframe_analysis": {
    "1M": {
      "interval": "1M",
      "trend": "neutral",
      "trend_strength": 50,
      "rsi": 39.09473123214259,
      "ema20": 2785.551955500005,
      "ema50": 2459.5072888244636,
      "key_levels": {
        "high": 4956.78,
        "low": 1385.05
      },
      "fib_levels": {
        "0.0": 4956.78,
        "0.236": 4113.85172,
        "0.382": 3592.37914,
        "0.5": 3170.915,
        "0.618": 2749.45086,
        "0.786": 2149.40022,
        "1.0": 1385.05
      },
      "latest_close": 1965.28,
      "higher_tf_bias": "unknown",
      "alignment_with_higher_tf": "misaligned"
    },
    "1w": {
      "interval": "1w",
      "trend": "bearish",
      "trend_strength": 130.0,
      "rsi": 29.40535945402533,
      "ema20": 2717.8923953606277,
      "ema50": 2980.427425115897,
      "key_levels": {
        "high": 4253.72,
        "low": 1747.8
      },
      "fib_levels": {
        "0.0": 4253.72,
        "0.236": 3662.32288,
        "0.382": 3296.45856,
        "0.5": 3000.76,
        "0.618": 2705.0614400000004,
        "0.786": 2284.0668800000003,
        "1.0": 1747.8
      },
      "latest_close": 1939.3,
      "higher_tf_bias": "bearish",
      "alignment_with_higher_tf": "aligned",
      "near_higher_tf_level": "none",
      "confidence": "high"
    },
    "1d": {
      "interval": "1d",
      "trend": "bearish",
      "trend_strength": 130.0,
      "rsi": 47.83072029451182,
      "ema20": 2020.3631673803598,
      "ema50": 2313.1408248188773,
      "key_levels": {
        "high": 2148.39,
        "low": 1800.0
      },
      "fib_levels": {
        "0.0": 2148.39,
        "0.236": 2066.1699599999997,
        "0.382": 2015.30502,
        "0.5": 1974.195,
        "0.618": 1933.0849799999999,
        "0.786": 1874.55546,
        "1.0": 1800.0
      },
      "latest_close": 1939.3,
      "higher_tf_bias": "bearish",
      "alignment_with_higher_tf": "aligned",
      "near_higher_tf_level": "none",
      "confidence": "high"
    },
    "4h": {
      "interval": "4h",
      "trend": "bearish",
      "trend_strength": 7.809741778304025,
      "rsi": 52.95758928571427,
      "ema20": 1958.430159353743,
      "ema50": 1959.6724174552946,
      "key_levels": {
        "high": 2054.8,
        "low": 1835.36
      },
      "fib_levels": {
        "0.0": 2054.8,
        "0.236": 2003.0121600000002,
        "0.382": 1970.9739200000001,
        "0.5": 1945.08,
        "0.618": 1919.18608,
        "0.786": 1882.32016,
        "1.0": 1835.36
      },
      "latest_close": 1947.97,
      "higher_tf_bias": "bearish",
      "alignment_with_higher_tf": "aligned",
      "near_higher_tf_level": "none",
      "at_higher_tf_fib": "0.618",
      "higher_tf_fib_price": 1933.0849799999999,
      "confidence": "high"
    },
    "1h": {
      "interval": "1h",
      "trend": "neutral",
      "trend_strength": 65.0,
      "rsi": 56.30549435876899,
      "ema20": 1956.8993288097251,
      "ema50": 1958.5806893424667,
      "key_levels": {
        "high": 1989.23,
        "low": 1907.41
      },
      "fib_levels": {
        "0.0": 1989.23,
        "0.236": 1969.92048,
        "0.382": 1957.97476,
        "0.5": 1948.3200000000002,
        "0.618": 1938.66524,
        "0.786": 1924.91948,
        "1.0": 1907.41
      },
      "latest_close": 1978.96,
      "higher_tf_bias": "neutral",
      "alignment_with_higher_tf": "aligned",
      "near_higher_tf_level": "none",
      "at_higher_tf_fib": "0.382",
      "higher_tf_fib_price": 1970.9739200000001,
      "confidence": "high"
    },
    "15m": {
      "interval": "15m",
      "trend": "neutral",
      "trend_strength": 35.0,
      "rsi": 72.500272598408,
      "ema20": 1948.320003086096,
      "ema50": 1949.9140945468462,
      "key_levels": {
        "high": 1985.48,
        "low": 1921.7
      },
      "fib_levels": {
        "0.0": 1985.48,
        "0.236": 1970.42792,
        "0.382": 1961.11604,
        "0.5": 1953.5900000000001,
        "0.618": 1946.06396,
        "0.786": 1935.3489200000001,
        "1.0": 1921.7
      },
      "latest_close": 1979.22,
      "higher_tf_bias": "bullish",
      "alignment_with_higher_tf": "misaligned",
      "near_higher_tf_level": "high",
      "higher_tf_level_value": 1989.23,
      "at_higher_tf_fib": "0.0",
      "higher_tf_fib_price": 1989.23,
      "confidence": "low"
    },
    "5m": {
      "interval": "5m",
      "trend": "bullish",
      "trend_strength": 37.345527626439946,
      "rsi": 86.89939579936714,
      "ema20": 1961.9546795657616,
      "ema50": 1950.5363020353573,
      "key_levels": {
        "high": 2010.96,
        "low": 1921.7
      },
      "fib_levels": {
        "0.0": 2010.96,
        "0.236": 1989.89464,
        "0.382": 1976.86268,
        "0.5": 1966.33,
        "0.618": 1955.7973200000001,
        "0.786": 1940.8016400000001,
        "1.0": 1921.7
      },
      "latest_close": 2006.57,
      "higher_tf_bias": "bullish",
      "alignment_with_higher_tf": "aligned",
      "near_higher_tf_level": "high",
      "higher_tf_level_value": 1985.48,
      "confidence": "high"
    }
  },
  "trade_setup": {
    "direction": "bearish",
    "entry_timeframe": "1h",
    "entry_price": 1978.96,
    "stop_loss": 1999.18,
    "target": 1800.0,
    "risk_reward": 8.85
  }
}