{
  "symbol": "BNBUSDT",
  "timestamp": "2026-02-28T19:13:03.109475",
  "overall_bias": "bearish",
  "confidence": 57.14285714285714,
  "timeframe_analysis": {
    "1M": {
      "interval": "1M",
      "trend": "neutral",
      "trend_strength": 50.0,
      "rsi": 45.263928702190555,
      "ema20": 711.2837354305645,
      "ema50": 530.7016018240746,
      "key_levels": {
        "high": 1375.11,
        "low": 183.4
      },
      "fib_levels": {
        "0.0": 1375.11,
        "0.236": 1093.86644,
        "0.382": 919.8767799999999,
        "0.5": 779.255,
        "0.618": 638.63322,
        "0.786": 438.42593999999997,
        "1.0": 183.4
      },
      "latest_close": 596.23,
      "higher_tf_bias": "unknown",
      "alignment_with_higher_tf": "aligned",
      "near_higher_tf_level": "none",
      "confidence": "medium",
      "at_higher_tf_fib": "0.618",
      "higher_tf_fib_price": 638.63322
    },
    "1w": {
      "interval": "1w",
      "trend": "neutral",
      "trend_strength": 50.0,
      "rsi": 25.096144165911596,
      "ema20": 801.6442736795652,
      "ema50": 793.7349938956299,
      "key_levels": {
        "high": 1375.11,
        "low": 520.0
      },
      "fib_levels": {
        "0.0": 1375.11,
        "0.236": 1173.30404,
        "0.382": 1048.45798,
        "0.5": 947.555,
        "0.618": 846.65202,
        "0.786": 702.9935399999999,
        "1.0": 520.0
      },
      "latest_close": 596.23,
      "higher_tf_bias": "unknown",
      "alignment_with_higher_tf": "aligned",
      "near_higher_tf_level": "none",
      "confidence": "high",
      "at_higher_tf_fib": "1.0",
      "higher_tf_fib_price": 520.0
    },
    "1d": {
      "interval": "1d",
      "trend": "bearish",
      "trend_strength": 100,
      "rsi": 40.60475161987043,
      "ema20": 634.4662398076716,
      "ema50": 713.9917748731613,
      "key_levels": {
        "high": 959.52,
        "low": 570.06
      },
      "fib_levels": {
        "0.0": 959.52,
        "0.236": 867.60744,
        "0.382": 810.74628,
        "0.5": 764.79,
        "0.618": 718.83372,
        "0.786": 653.40444,
        "1.0": 570.06
      },
      "latest_close": 596.23,
      "higher_tf_bias": "unknown",
      "alignment_with_higher_tf": "aligned",
      "near_higher_tf_level": "none",
      "confidence": "high",
      "at_higher_tf_fib": "1.0",
      "higher_tf_fib_price": 570.06
    },
    "4h": {
      "interval": "4h",
      "trend": "bearish",
      "trend_strength": 96.79576616900027,
      "rsi": 20.798973795125548,
      "ema20": 612.4099950262829,
      "ema50": 613.4550772594675,
      "key_levels": {
        "high": 640.55,
        "low": 577.06
      },
      "fib_levels": {
        "0.0": 640.55,
        "0.236": 625.5663599999999,
        "0.382": 616.2968199999999,
        "0.5": 608.805,
        "0.618": 601.31318,
        "0.786": 590.64686,
        "1.0": 577.06
      },
      "latest_close": 596.0,
      "higher_tf_bias": "bearish",
      "alignment_with_higher_tf": "aligned",
      "near_higher_tf_level": "none",
      "confidence": "high",
      "at_higher_tf_fib": "0.618",
      "higher_tf_fib_price": 601.31318
    },
    "1h": {
      "interval": "1h",
      "trend": "bearish",
      "trend_strength": 85.38797093238315,
      "rsi": 33.51504579153955,
      "ema20": 605.3247191834479,
      "ema50": 611.8609665970679,
      "key_levels": {
        "high": 633.65,
        "low": 588.64
      },
      "fib_levels": {
        "0.0": 633.65,
        "0.236": 623.02764,
        "0.382": 616.45618,
        "0.5": 611.145,
        "0.618": 605.83382,
        "0.786": 598.27214,
        "1.0": 588.64
      },
      "latest_close": 596.01,
      "higher_tf_bias": "bearish",
      "alignment_with_higher_tf": "aligned",
      "near_higher_tf_level": "fib",
      "confidence": "high",
      "higher_tf_level_value": 598.27214,
      "at_higher_tf_fib": "0.786",
      "higher_tf_fib_price": 598.27214
    },
    "15m": {
      "interval": "15m",
      "trend": "bearish",
      "trend_strength": 70.52395348375364,
      "rsi": 40.76595744680849,
      "ema20": 596.3224452226149,
      "ema50": 602.7355853291429,
      "key_levels": {
        "high": 615.6,
        "low": 588.64
      },
      "fib_levels": {
        "0.0": 615.6,
        "0.236": 609.23744,
        "0.382": 605.30128,
        "0.5": 602.12,
        "0.618": 598.93872,
        "0.786": 594.40944,
        "1.0": 588.64
      },
      "latest_close": 596.01,
      "higher_tf_bias": "bearish",
      "alignment_with_higher_tf": "aligned",
      "near_higher_tf_level": "fib",
      "confidence": "high",
      "higher_tf_level_value": 598.93872,
      "at_higher_tf_fib": "0.786",
      "higher_tf_fib_price": 594.40944
    },
    "5m": {
      "interval": "5m",
      "trend": "neutral",
      "trend_strength": 50.0,
      "rsi": 82.44897959183658,
      "ema20": 593.8092201289202,
      "ema50": 595.3724776129608,
      "key_levels": {
        "high": 601.46,
        "low": 588.64
      },
      "fib_levels": {
        "0.0": 601.46,
        "0.236": 598.43448,
        "0.382": 596.56276,
        "0.5": 595.05,
        "0.618": 593.53724,
        "0.786": 591.38348,
        "1.0": 588.64
      },
      "latest_close": 596.0,
      "higher_tf_bias": "bearish",
      "alignment_with_higher_tf": "misaligned",
      "near_higher_tf_level": "fib",
      "confidence": "medium",
      "higher_tf_level_value": 598.43448,
      "at_higher_tf_fib": "0.382",
      "higher_tf_fib_price": 596.56276
    }
  },
  "trade_setup": {
    "bias": "neutral",
    "confidence": 50.0,
    "entry_zone": {
      "min": 593.53724,
      "max": 595.05
    },
    "stop_loss": 591.38348,
    "take_profit": 596.56276,
    "recommended_timeframe": "5m"
  }
}