{
  "symbol": "BNBUSDT",
  "timestamp": "2026-02-26T00:28:06.552901",
  "timeframes": {
    "1w": {
      "timestamp": 1771804800000,
      "datetime": "2026-02-23T00:00:00",
      "open": 614.8,
      "high": 616.0,
      "low": 583.13,
      "close": 590.7,
      "volume": 87047.376,
      "category": "Long-Term",
      "ema_fast": 793.5707825918486,
      "ema_slow": 561.410180608926,
      "rsi": 24.819785734198888,
      "macd": -60.86558714061118,
      "macd_signal": -15.16132040509731,
      "macd_histogram": -45.70426673551387,
      "atr": 82.90214285714285,
      "vwap": 158.79482267541533,
      "volume_sma": 1803538.109845,
      "volume_ratio": 0.04826478327507093,
      "trend": "Neutral"
    },
    "1d": {
      "timestamp": 1771977600000,
      "datetime": "2026-02-25T00:00:00",
      "open": 583.61,
      "high": 583.94,
      "low": 581.6,
      "close": 582.52,
      "volume": 2757.05,
      "category": "Daily",
      "ema_fast": 638.7364529491817,
      "ema_slow": 725.4363095611225,
      "rsi": 42.10818478998334,
      "macd": -46.35190798181873,
      "macd_signal": -52.180715480005176,
      "macd_histogram": 5.82880749818645,
      "atr": 22.50999999999999,
      "vwap": 772.3884553565439,
      "volume_sma": 142740.81325,
      "volume_ratio": 0.019315078408382265,
      "trend": "Neutral"
    },
    "4h": {
      "timestamp": 1772020800000,
      "datetime": "2026-02-25T12:00:00",
      "open": 605.0,
      "high": 609.41,
      "low": 604.58,
      "close": 608.25,
      "volume": 4063.736,
      "category": "Medium",
      "ema_fast": 596.1697699211729,
      "ema_slow": 599.6390065524537,
      "rsi": 61.25151883353584,
      "macd": -4.7874304823257035,
      "macd_signal": -6.2061170370502365,
      "macd_histogram": 1.418686554724533,
      "atr": 6.802142857142834,
      "vwap": 805.1690120987884,
      "volume_sma": 8195.950850000001,
      "volume_ratio": 0.4958223974708193,
      "trend": "Neutral"
    },
    "1h": {
      "timestamp": 1772031600000,
      "datetime": "2026-02-25T15:00:00",
      "open": 618.69,
      "high": 620.72,
      "low": 616.0,
      "close": 620.29,
      "volume": 7621.189,
      "category": "Short",
      "ema_fast": 608.1210663338945,
      "ema_slow": 599.8332279125963,
      "rsi": 74.71689895470365,
      "macd": 5.957366101093044,
      "macd_signal": 3.175437735631646,
      "macd_histogram": 2.7819283654613978,
      "atr": 4.537857142857133,
      "vwap": 647.6191656680696,
      "volume_sma": 3965.0951,
      "volume_ratio": 1.9220696623392464,
      "trend": "Bullish"
    },
    "15m": {
      "timestamp": 1772033400000,
      "datetime": "2026-02-25T15:30:00",
      "open": 618.28,
      "high": 620.72,
      "low": 617.39,
      "close": 620.29,
      "volume": 2434.94,
      "category": "Ultra-Short",
      "ema_fast": 616.094683278179,
      "ema_slow": 604.7778290804075,
      "ema_mid": 611.6545571947293,
      "rsi": 76.96381288614295,
      "atr": 2.9328571428571553,
      "vwap": 605.6587139088358,
      "volume_sma": 2294.4177,
      "volume_ratio": 1.0612452998423085,
      "trend": "Bullish"
    },
    "5m": {
      "timestamp": 1772033700000,
      "datetime": "2026-02-25T15:35:00",
      "open": 619.27,
      "high": 620.72,
      "low": 619.27,
      "close": 620.29,
      "volume": 400.514,
      "category": "Scalp",
      "ema_fast": 618.0184269181859,
      "rsi": 100.0,
      "atr": 1.838000000000011,
      "vwap": 595.9316147565519,
      "volume_sma": 1174.4941000000001,
      "volume_ratio": 0.34100980158180444,
      "trend": "Bullish"
    }
  },
  "compass_score": {
    "total_score": 15.5,
    "timeframe_scores": {
      "1w": 20,
      "1d": -10,
      "4h": 0,
      "1h": 40,
      "15m": 60,
      "5m": 60
    },
    "signal": "Flat",
    "confidence": "Low",
    "alignment": "Moderately Bullish"
  },
  "futures_data": {
    "oi": 503092.12,
    "oi_value": 312696907.186,
    "funding_rate": 0.0,
    "mark_price": 621.54,
    "long_account": 0.7065,
    "short_account": 0.2935,
    "ls_ratio": 2.4072
  },
  "trade_setup": null,
  "summary": {
    "signal": "Flat",
    "confidence": "Low",
    "alignment": "Moderately Bullish",
    "score": 15.5
  }
}