{
  "symbol": "BTCUSDT",
  "timestamp": "2026-02-26T00:48:05.484937",
  "timeframes": {
    "1w": {
      "timestamp": 1771804800000,
      "datetime": "2026-02-23T00:00:00",
      "open": 67643.39,
      "high": 67684.86,
      "low": 64290.71,
      "close": 64942.45,
      "volume": 10928.15012,
      "category": "Long-Term",
      "ema_fast": 92082.41070068281,
      "ema_slow": 68338.83599465001,
      "rsi": 24.228456805284964,
      "macd": -9455.462668561784,
      "macd_signal": -6610.334734483103,
      "macd_histogram": -2845.1279340786814,
      "atr": 7828.822142857144,
      "vwap": 28552.788744619396,
      "volume_sma": 143994.59287,
      "volume_ratio": 0.07589278112592784,
      "trend": "Bearish"
    },
    "1d": {
      "timestamp": 1771977600000,
      "datetime": "2026-02-25T00:00:00",
      "open": 64058.15,
      "high": 64080.81,
      "low": 63913.27,
      "close": 64042.58,
      "volume": 98.88705,
      "category": "Daily",
      "ema_fast": 69079.35170327354,
      "ema_slow": 76374.96794365565,
      "rsi": 38.768700113940795,
      "macd": -3801.315318673791,
      "macd_signal": -4150.317629842712,
      "macd_histogram": 349.00231116892155,
      "atr": 2162.0364285714277,
      "vwap": 94411.37928347632,
      "volume_sma": 22290.895481,
      "volume_ratio": 0.004436208051143031,
      "trend": "Neutral"
    },
    "4h": {
      "timestamp": 1772035200000,
      "datetime": "2026-02-25T16:00:00",
      "open": 67412.32,
      "high": 68100.01,
      "low": 67404.0,
      "close": 67988.15,
      "volume": 1473.13148,
      "category": "Medium",
      "ema_fast": 65517.32820120302,
      "ema_slow": 65586.02852495878,
      "rsi": 59.11397056400319,
      "macd": -334.4562781207933,
      "macd_signal": -713.2222409739431,
      "macd_histogram": 378.76596285314986,
      "atr": 970.3014285714281,
      "vwap": 81053.74398357132,
      "volume_sma": 1101.711787,
      "volume_ratio": 1.337129635339011,
      "trend": "Neutral"
    },
    "1h": {
      "timestamp": 1772035200000,
      "datetime": "2026-02-25T16:00:00",
      "open": 67412.32,
      "high": 68100.01,
      "low": 67404.0,
      "close": 67988.15,
      "volume": 1473.13148,
      "category": "Short",
      "ema_fast": 66415.91351007503,
      "ema_slow": 65499.96197503033,
      "rsi": 69.45408434263581,
      "macd": 680.6723442298899,
      "macd_signal": 422.6423363396641,
      "macd_histogram": 258.03000789022576,
      "atr": 513.2342857142856,
      "vwap": 68967.12783067428,
      "volume_sma": 576.2949675,
      "volume_ratio": 2.5562109042709973,
      "trend": "Bullish"
    },
    "15m": {
      "timestamp": 1772037000000,
      "datetime": "2026-02-25T16:30:00",
      "open": 67872.17,
      "high": 68000.0,
      "low": 67823.52,
      "close": 67985.22,
      "volume": 175.88319,
      "category": "Ultra-Short",
      "ema_fast": 67351.09120635025,
      "ema_slow": 66029.79890254654,
      "ema_mid": 66741.1582143672,
      "rsi": 89.85774374970498,
      "atr": 396.422857142856,
      "vwap": 66238.92053309517,
      "volume_sma": 417.5570715,
      "volume_ratio": 0.4212195218444528,
      "trend": "Bullish"
    },
    "5m": {
      "timestamp": 1772037300000,
      "datetime": "2026-02-25T16:35:00",
      "open": 67856.4,
      "high": 68000.0,
      "low": 67856.4,
      "close": 67985.22,
      "volume": 22.43999,
      "category": "Scalp",
      "ema_fast": 67745.50358386536,
      "rsi": 77.56212406149953,
      "atr": 231.57200000000012,
      "vwap": 64971.23106817094,
      "volume_sma": 192.91171300000002,
      "volume_ratio": 0.11632258949460471,
      "trend": "Bullish"
    }
  },
  "compass_score": {
    "total_score": 7.0,
    "timeframe_scores": {
      "1w": -20,
      "1d": -10,
      "4h": 10,
      "1h": 50,
      "15m": 60,
      "5m": 60
    },
    "signal": "Flat",
    "confidence": "Low",
    "alignment": "Moderately Bullish"
  },
  "futures_data": {
    "oi": 79325.827,
    "oi_value": 5344545015.35292,
    "funding_rate": -9.68e-06,
    "mark_price": 67376.31104348,
    "long_account": 0.6399,
    "short_account": 0.3601,
    "ls_ratio": 1.777
  },
  "trade_setup": null,
  "summary": {
    "signal": "Flat",
    "confidence": "Low",
    "alignment": "Moderately Bullish",
    "score": 7.0
  }
}