{
  "BTCUSDT": {
    "symbol": "BTCUSDT",
    "timestamp": "2026-02-26T15:38:06.081979",
    "timeframes": {
      "1w": {
        "timestamp": 1771804800000,
        "datetime": "2026-02-23T00:00:00",
        "open": 67643.39,
        "high": 67684.86,
        "low": 64290.71,
        "close": 64942.45,
        "volume": 10928.15012,
        "category": "Long-Term",
        "ema_fast": 92082.41070068281,
        "ema_slow": 68338.83599465001,
        "rsi": 24.228456805284964,
        "macd": -9455.462668561784,
        "macd_signal": -6610.334734483103,
        "macd_histogram": -2845.1279340786814,
        "atr": 7828.822142857144,
        "vwap": 28552.788744619396,
        "volume_sma": 143994.59287,
        "volume_ratio": 0.07589278112592784,
        "trend": "Bearish"
      },
      "1d": {
        "timestamp": 1772064000000,
        "datetime": "2026-02-26T00:00:00",
        "open": 67988.04,
        "high": 68539.17,
        "low": 67727.52,
        "close": 68197.05,
        "volume": 1019.1502,
        "category": "Daily",
        "ema_fast": 68995.32296962844,
        "ema_slow": 76054.26527919856,
        "rsi": 55.702516847914346,
        "macd": -3421.6438779298915,
        "macd_signal": -4004.5828794601484,
        "macd_histogram": 582.939001530257,
        "atr": 2248.0414285714273,
        "vwap": 94409.10513183543,
        "volume_sma": 17714.8922255,
        "volume_ratio": 0.057530702813589074,
        "trend": "Neutral"
      },
      "4h": {
        "timestamp": 1772078400000,
        "datetime": "2026-02-26T04:00:00",
        "open": 68216.87,
        "high": 68860.0,
        "low": 68179.62,
        "close": 68617.23,
        "volume": 568.0625,
        "category": "Medium",
        "ema_fast": 67022.94875901594,
        "ema_slow": 66340.39282866924,
        "rsi": 69.44225596543873,
        "macd": 332.2707843920507,
        "macd_signal": -275.10036740571365,
        "macd_histogram": 607.3711517977644,
        "atr": 1000.12,
        "vwap": 81036.30429079825,
        "volume_sma": 946.6950444999999,
        "volume_ratio": 0.6000480337361691,
        "trend": "Bullish"
      },
      "1h": {
        "timestamp": 1772089200000,
        "datetime": "2026-02-26T07:00:00",
        "open": 68176.75,
        "high": 68235.29,
        "low": 68167.91,
        "close": 68235.29,
        "volume": 13.31146,
        "category": "Short",
        "ema_fast": 68322.13297028004,
        "ema_slow": 67578.47943267568,
        "rsi": 46.78565496230214,
        "macd": 701.9439291336312,
        "macd_signal": 832.0706762335442,
        "macd_histogram": -130.12674709991302,
        "atr": 674.3500000000006,
        "vwap": 68961.58229345482,
        "volume_sma": 840.9510505000001,
        "volume_ratio": 0.015829054487874736,
        "trend": "Neutral"
      },
      "15m": {
        "timestamp": 1772089200000,
        "datetime": "2026-02-26T07:00:00",
        "open": 68176.75,
        "high": 68235.29,
        "low": 68167.91,
        "close": 68235.29,
        "volume": 13.31146,
        "category": "Ultra-Short",
        "ema_fast": 68287.93313771994,
        "ema_slow": 68168.01971366639,
        "ema_mid": 68321.1921599092,
        "rsi": 37.9816837605153,
        "atr": 140.8157142857152,
        "vwap": 66453.478844609,
        "volume_sma": 115.91263150000002,
        "volume_ratio": 0.11484046067921423,
        "trend": "Neutral"
      },
      "5m": {
        "timestamp": 1772089200000,
        "datetime": "2026-02-26T07:00:00",
        "open": 68176.75,
        "high": 68230.56,
        "low": 68167.91,
        "close": 68226.32,
        "volume": 13.21239,
        "category": "Scalp",
        "ema_fast": 68220.17175302302,
        "rsi": 50.21099191621376,
        "atr": 89.18399999999966,
        "vwap": 65602.95038254678,
        "volume_sma": 39.52562350000001,
        "volume_ratio": 0.33427404377314873,
        "trend": "Bullish"
      }
    },
    "compass_score": {
      "total_score": 4.5,
      "timeframe_scores": {
        "1w": -20,
        "1d": 0,
        "4h": 30,
        "1h": 0,
        "15m": 30,
        "5m": 80
      },
      "signal": "Flat",
      "confidence": "Low",
      "alignment": "Strongly Bullish"
    },
    "futures_data": {
      "oi": 79602.848,
      "oi_value": 5424637837.664328,
      "funding_rate": -1.998e-05,
      "mark_price": 67953.96802174,
      "long_account": 0.6085,
      "short_account": 0.3915,
      "ls_ratio": 1.5543
    },
    "trade_setup": null,
    "summary": {
      "signal": "Flat",
      "confidence": "Low",
      "alignment": "Strongly Bullish",
      "score": 4.5
    }
  },
  "ETHUSDT": {
    "symbol": "ETHUSDT",
    "timestamp": "2026-02-26T15:38:06.115938",
    "timeframes": {
      "1w": {
        "timestamp": 1771804800000,
        "datetime": "2026-02-23T00:00:00",
        "open": 1957.82,
        "high": 1958.33,
        "low": 1847.46,
        "close": 1864.5,
        "volume": 166590.3597,
        "category": "Long-Term",
        "ema_fast": 3019.973007492433,
        "ema_slow": 2595.7848805944186,
        "rsi": 28.385767237722916,
        "macd": -385.59068186688364,
        "macd_signal": -226.34765490150417,
        "macd_histogram": -159.24302696537947,
        "atr": 370.45857142857136,
        "vwap": 1698.1527551756108,
        "volume_sma": 3365062.960045,
        "volume_ratio": 0.04950586710501614,
        "trend": "Bearish"
      },
      "1d": {
        "timestamp": 1772064000000,
        "datetime": "2026-02-26T00:00:00",
        "open": 2057.48,
        "high": 2076.6,
        "low": 2047.83,
        "close": 2060.01,
        "volume": 20812.1717,
        "category": "Daily",
        "ema_fast": 2044.4205988782858,
        "ema_slow": 2371.203370161268,
        "rsi": 57.959351670498755,
        "macd": -149.50686787689483,
        "macd_signal": -183.57517530186004,
        "macd_histogram": 34.06830742496521,
        "atr": 89.31571428571428,
        "vwap": 3002.469381662285,
        "volume_sma": 381207.21767000004,
        "volume_ratio": 0.05459542929750215,
        "trend": "Neutral"
      },
      "4h": {
        "timestamp": 1772078400000,
        "datetime": "2026-02-26T04:00:00",
        "open": 2054.55,
        "high": 2082.81,
        "low": 2051.92,
        "close": 2077.51,
        "volume": 23015.1635,
        "category": "Medium",
        "ema_fast": 1990.210021762592,
        "ema_slow": 1946.6325764470528,
        "rsi": 79.61593729588506,
        "macd": 28.276662024676853,
        "macd_signal": -0.5846847938477184,
        "macd_histogram": 28.86134681852457,
        "atr": 33.54428571428569,
        "vwap": 2620.0240163527637,
        "volume_sma": 16486.671435000004,
        "volume_ratio": 1.3959860600570035,
        "trend": "Bullish"
      },
      "1h": {
        "timestamp": 1772089200000,
        "datetime": "2026-02-26T07:00:00",
        "open": 2062.54,
        "high": 2065.3,
        "low": 2061.96,
        "close": 2065.29,
        "volume": 333.6408,
        "category": "Short",
        "ema_fast": 2062.222232003144,
        "ema_slow": 2022.0809352353745,
        "rsi": 50.27643572246853,
        "macd": 37.264100470616086,
        "macd_signal": 42.80310672791415,
        "macd_histogram": -5.5390062572980625,
        "atr": 26.12142857142854,
        "vwap": 2046.567377925571,
        "volume_sma": 19746.998614999997,
        "volume_ratio": 0.016895772694619195,
        "trend": "Bullish"
      },
      "15m": {
        "timestamp": 1772089200000,
        "datetime": "2026-02-26T07:00:00",
        "open": 2062.54,
        "high": 2065.3,
        "low": 2061.96,
        "close": 2065.29,
        "volume": 333.6408,
        "category": "Ultra-Short",
        "ema_fast": 2064.176931058337,
        "ema_slow": 2052.882751245513,
        "ema_mid": 2063.1900016165046,
        "rsi": 55.23906408952061,
        "atr": 5.764285714285701,
        "vwap": 1943.9485393452321,
        "volume_sma": 3014.3269050000004,
        "volume_ratio": 0.11068500879800891,
        "trend": "Bullish"
      },
      "5m": {
        "timestamp": 1772089200000,
        "datetime": "2026-02-26T07:00:00",
        "open": 2062.54,
        "high": 2065.3,
        "low": 2061.96,
        "close": 2065.29,
        "volume": 333.6408,
        "category": "Scalp",
        "ema_fast": 2064.1667269193586,
        "rsi": 65.76980568012041,
        "atr": 3.5140000000001237,
        "vwap": 1926.9427335547668,
        "volume_sma": 892.8063750000001,
        "volume_ratio": 0.3736989445219855,
        "trend": "Bullish"
      }
    },
    "compass_score": {
      "total_score": 16.7,
      "timeframe_scores": {
        "1w": -20,
        "1d": 0,
        "4h": 30,
        "1h": 60,
        "15m": 80,
        "5m": 70
      },
      "signal": "Flat",
      "confidence": "Low",
      "alignment": "Strongly Bullish"
    },
    "futures_data": {
      "oi": 1902891.367,
      "oi_value": 3922886668.72518,
      "funding_rate": 7.787e-05,
      "mark_price": 2056.85373643,
      "long_account": 0.5947,
      "short_account": 0.4053,
      "ls_ratio": 1.4673
    },
    "trade_setup": null,
    "summary": {
      "signal": "Flat",
      "confidence": "Low",
      "alignment": "Strongly Bullish",
      "score": 16.7
    }
  },
  "BNBUSDT": {
    "symbol": "BNBUSDT",
    "timestamp": "2026-02-26T15:38:06.149623",
    "timeframes": {
      "1w": {
        "timestamp": 1771804800000,
        "datetime": "2026-02-23T00:00:00",
        "open": 614.8,
        "high": 616.0,
        "low": 583.13,
        "close": 590.7,
        "volume": 87047.376,
        "category": "Long-Term",
        "ema_fast": 793.5707825918486,
        "ema_slow": 561.410180608926,
        "rsi": 24.819785734198888,
        "macd": -60.86558714061118,
        "macd_signal": -15.16132040509731,
        "macd_histogram": -45.70426673551387,
        "atr": 82.90214285714285,
        "vwap": 158.79482267541533,
        "volume_sma": 1803538.109845,
        "volume_ratio": 0.04826478327507093,
        "trend": "Neutral"
      },
      "1d": {
        "timestamp": 1772064000000,
        "datetime": "2026-02-26T00:00:00",
        "open": 629.42,
        "high": 633.83,
        "low": 627.54,
        "close": 629.35,
        "volume": 7151.532,
        "category": "Daily",
        "ema_fast": 637.8425050492597,
        "ema_slow": 721.668218990098,
        "rsi": 53.713383962915486,
        "macd": -41.620737483804305,
        "macd_signal": -50.068719880765,
        "macd_histogram": 8.447982396960697,
        "atr": 24.727142857142855,
        "vwap": 772.3822579893498,
        "volume_sma": 113432.26020000002,
        "volume_ratio": 0.063046720460217,
        "trend": "Neutral"
      },
      "4h": {
        "timestamp": 1772078400000,
        "datetime": "2026-02-26T04:00:00",
        "open": 627.88,
        "high": 632.47,
        "low": 627.45,
        "close": 631.0,
        "volume": 3570.584,
        "category": "Medium",
        "ema_fast": 615.7845457597125,
        "ema_slow": 608.9797599565969,
        "rsi": 74.86658195679797,
        "macd": 3.8138550841758843,
        "macd_signal": -1.610296327055637,
        "macd_histogram": 5.424151411231521,
        "atr": 6.962142857142859,
        "vwap": 804.8498135695513,
        "volume_sma": 7132.3336,
        "volume_ratio": 0.5006193204423304,
        "trend": "Bullish"
      },
      "1h": {
        "timestamp": 1772089200000,
        "datetime": "2026-02-26T07:00:00",
        "open": 626.61,
        "high": 627.23,
        "low": 626.42,
        "close": 627.23,
        "volume": 73.738,
        "category": "Short",
        "ema_fast": 628.0356033159535,
        "ema_slow": 620.9207512776345,
        "rsi": 49.67559943582508,
        "macd": 6.714337274921149,
        "macd_signal": 7.971360111665607,
        "macd_histogram": -1.2570228367444578,
        "atr": 5.372142857142868,
        "vwap": 647.2358933949779,
        "volume_sma": 6221.83615,
        "volume_ratio": 0.011851485352921099,
        "trend": "Neutral"
      },
      "15m": {
        "timestamp": 1772089200000,
        "datetime": "2026-02-26T07:00:00",
        "open": 626.61,
        "high": 627.23,
        "low": 626.42,
        "close": 627.23,
        "volume": 73.738,
        "category": "Ultra-Short",
        "ema_fast": 627.5338914369758,
        "ema_slow": 626.7568409841956,
        "ema_mid": 628.0797291639633,
        "rsi": 47.00665188470086,
        "atr": 1.317142857142861,
        "vwap": 608.1866607729429,
        "volume_sma": 932.0298499999999,
        "volume_ratio": 0.07911549184824929,
        "trend": "Neutral"
      },
      "5m": {
        "timestamp": 1772089200000,
        "datetime": "2026-02-26T07:00:00",
        "open": 626.61,
        "high": 627.23,
        "low": 626.42,
        "close": 627.23,
        "volume": 73.703,
        "category": "Scalp",
        "ema_fast": 627.0220163908899,
        "rsi": 56.93779904306085,
        "atr": 0.8120000000000118,
        "vwap": 602.38286922328,
        "volume_sma": 313.6402500000001,
        "volume_ratio": 0.23499216060438666,
        "trend": "Bullish"
      }
    },
    "compass_score": {
      "total_score": 15.2,
      "timeframe_scores": {
        "1w": 20,
        "1d": 0,
        "4h": 20,
        "1h": 0,
        "15m": 40,
        "5m": 80
      },
      "signal": "Flat",
      "confidence": "Low",
      "alignment": "Moderately Bullish"
    },
    "futures_data": {
      "oi": 503277.49,
      "oi_value": 315546538.2794789,
      "funding_rate": 0.0,
      "mark_price": 629.78524179,
      "long_account": 0.6856,
      "short_account": 0.3144,
      "ls_ratio": 2.1807
    },
    "trade_setup": null,
    "summary": {
      "signal": "Flat",
      "confidence": "Low",
      "alignment": "Moderately Bullish",
      "score": 15.2
    }
  }
}